gpq/__init__.py
gpq/gpq.py
gpq-0.4.0.dist-info/WHEEL
gpq-0.4.0.dist-info/METADATA
gpq-0.4.0.dist-info/RECORD
