Metadata-Version: 2.1
Name: gpq
Version: 0.4.0
Summary: 
License: MIT
Author: yohan-pg
Author-email: pg.yohan@gmail.com
Requires-Python: >=3.8,<4.0
Classifier: License :: OSI Approved :: MIT License
Classifier: Programming Language :: Python :: 3
Classifier: Programming Language :: Python :: 3.10
Classifier: Programming Language :: Python :: 3.8
Classifier: Programming Language :: Python :: 3.9
Requires-Dist: longprocess (>=0.2.2,<0.3.0)
Requires-Dist: nvsmi (>=0.4.2,<0.5.0)
Requires-Dist: persistQueue (>=0.1.6,<0.2.0)
Requires-Dist: psutil (>=5.9.1,<6.0.0)
Requires-Dist: torch (>=1.11.0,<2.0.0)
